{
  "$schema": "https://schemas.wp.org/trunk/block.json",
  "apiVersion": 3,
  "name": "tenthousandcuts/masonryartarchive",
  "version": "0.1.0",
  "title": "Masonry art archive",
  "category": "theme",
  "icon": "layout",
  "description": "Randomized Masonry Grid of Artwork Posts",
  "example": {},
  "supports": {
    "html": false
  },
  "textdomain": "masonryartarchive",
  "editorScript": "file:./index.js",
  "editorStyle": "file:./index.css",
  "style": "file:./style-index.css",
  "render": "file:./render.php",
  "viewScript": "file:./view.js"
}